rtralm/RTRAConnector.py
rtralm/__init__.py
rtralm-0.2.dist-info/METADATA
rtralm-0.2.dist-info/WHEEL
rtralm-0.2.dist-info/top_level.txt
rtralm-0.2.dist-info/RECORD
